verticapy/__init__.py
verticapy/_help.py
verticapy/_typing.py
verticapy/_config/__init__.py
verticapy/_config/config.py
verticapy/_config/validators.py
verticapy/_utils/__init__.py
verticapy/_utils/_display.py
verticapy/_utils/_gen.py
verticapy/_utils/_inspect_statistics.py
verticapy/_utils/_logo.py
verticapy/_utils/_map.py
verticapy/_utils/_object.py
verticapy/_utils/_parsers.py
verticapy/_utils/_print.py
verticapy/_utils/_sql/__init__.py
verticapy/_utils/_sql/_cast.py
verticapy/_utils/_sql/_check.py
verticapy/_utils/_sql/_collect.py
verticapy/_utils/_sql/_dblink.py
verticapy/_utils/_sql/_display.py
verticapy/_utils/_sql/_format.py
verticapy/_utils/_sql/_merge.py
verticapy/_utils/_sql/_random.py
verticapy/_utils/_sql/_sys.py
verticapy/_utils/_sql/_vertica_version.py
verticapy/chart/__init__.py
verticapy/connection/__init__.py
verticapy/connection/connect.py
verticapy/connection/errors.py
verticapy/connection/external.py
verticapy/connection/global_connection.py
verticapy/connection/oauth_manager.py
verticapy/connection/read.py
verticapy/connection/utils.py
verticapy/connection/write.py
verticapy/core/__init__.py
verticapy/core/parsers/__init__.py
verticapy/core/parsers/_utils.py
verticapy/core/parsers/all.py
verticapy/core/parsers/avro.py
verticapy/core/parsers/csv.py
verticapy/core/parsers/json.py
verticapy/core/parsers/pandas.py
verticapy/core/parsers/shp.py
verticapy/core/string_sql/__init__.py
verticapy/core/string_sql/base.py
verticapy/core/tablesample/__init__.py
verticapy/core/tablesample/base.py
verticapy/core/vdataframe/__init__.py
verticapy/core/vdataframe/_aggregate.py
verticapy/core/vdataframe/_corr.py
verticapy/core/vdataframe/_encoding.py
verticapy/core/vdataframe/_eval.py
verticapy/core/vdataframe/_fill.py
verticapy/core/vdataframe/_filter.py
verticapy/core/vdataframe/_io.py
verticapy/core/vdataframe/_join_union_sort.py
verticapy/core/vdataframe/_machine_learning.py
verticapy/core/vdataframe/_math.py
verticapy/core/vdataframe/_multiprocessing.py
verticapy-1.1.1.dist-info/LICENSE.txt
verticapy-1.1.1.dist-info/METADATA
verticapy-1.1.1.dist-info/WHEEL
verticapy-1.1.1.dist-info/top_level.txt
verticapy-1.1.1.dist-info/RECORD
