Metadata-Version: 2.2
Name: verticapy
Version: 1.1.1
Summary: VerticaPy simplifies data exploration, data cleaning, and machine learning in Vertica.
Home-page: https://github.com/vertica/VerticaPy
Author: Badr Ouali
Author-email: badr.ouali@outlook.fr
Keywords: vertica python ml data science machine learning statistics database
Classifier: Intended Audience :: Science/Research
Classifier: Intended Audience :: Developers
Classifier: Programming Language :: Python :: 3.9
Classifier: Programming Language :: Python :: 3.10
Classifier: Programming Language :: Python :: 3.11
Classifier: Programming Language :: Python :: 3.12
Classifier: Topic :: Database
Classifier: License :: OSI Approved :: Apache Software License
Classifier: Operating System :: OS Independent
Requires-Python: >=3.9
License-File: LICENSE.txt
Requires-Dist: graphviz>=0.9.0
Requires-Dist: matplotlib>=3.5.2
Requires-Dist: numpy>=1.11.0
Requires-Dist: pandas>=0.23.0
Requires-Dist: plotly>=5.10.0
Requires-Dist: scipy>=1.0.0
Requires-Dist: tqdm>=4.0.0
Requires-Dist: vertica-highcharts>=0.1.4
Requires-Dist: vertica-python>=1.2.0
Requires-Dist: plotly>=5.10.0
Requires-Dist: pyyaml>=6.0.1
Requires-Dist: requests>=2.32.2
Requires-Dist: urllib3>=2.2.1
Provides-Extra: all
Requires-Dist: descartes>=1.0.0; extra == "all"
Requires-Dist: geopandas>=0.8.0; extra == "all"
Requires-Dist: shapely>=1.6.0; extra == "all"
Requires-Dist: pyarrow>=14.0.0; extra == "all"
Dynamic: author
Dynamic: author-email
Dynamic: classifier
Dynamic: description
Dynamic: description-content-type
Dynamic: home-page
Dynamic: keywords
Dynamic: provides-extra
Dynamic: requires-dist
Dynamic: requires-python
Dynamic: summary
